AUTHORS.txt
LICENSE.txt
MANIFEST.in
README.md
setup.py
menpowidgets/__init__.py
menpowidgets/_static_version.py
menpowidgets/_version.py
menpowidgets/abstract.py
menpowidgets/base.py
menpowidgets/checks.py
menpowidgets/items.py
menpowidgets/options.py
menpowidgets/style.py
menpowidgets/tools.py
menpowidgets/utils.py
menpowidgets.egg-info/PKG-INFO
menpowidgets.egg-info/SOURCES.txt
menpowidgets.egg-info/dependency_links.txt
menpowidgets.egg-info/requires.txt
menpowidgets.egg-info/top_level.txt
menpowidgets/js/webcam.js
menpowidgets/logos/menpoproject_danger.png
menpowidgets/logos/menpoproject_info.png
menpowidgets/logos/menpoproject_minimal.png
menpowidgets/logos/menpoproject_success.png
menpowidgets/logos/menpoproject_warning.png
menpowidgets/menpofitwidgets/__init__.py
menpowidgets/menpofitwidgets/base.py