Metadata-Version: 1.0
Name: menpowidgets
Version: 0.4.1
Summary: Menpo's Jupyter widgets for fancy visualization
Home-page: UNKNOWN
Author: The Menpo Development Team
Author-email: hello@menpo.org
License: UNKNOWN
Platform: UNKNOWN
